marvelfansapi/__init__.py
marvelfansapi/marvel_oops.py
marvelfansapi/setup.py
marvelfansapi-0.1.dist-info/METADATA
marvelfansapi-0.1.dist-info/WHEEL
marvelfansapi-0.1.dist-info/top_level.txt
marvelfansapi-0.1.dist-info/RECORD
